pywe_marketcode/__init__.py
pywe_marketcode/pywemarketcode.py
pywe_marketcode-1.0.3.dist-info/METADATA
pywe_marketcode-1.0.3.dist-info/WHEEL
pywe_marketcode-1.0.3.dist-info/top_level.txt
pywe_marketcode-1.0.3.dist-info/RECORD
