Metadata-Version: 2.1
Name: pywe-marketcode
Version: 1.0.3
Summary: Wechat MarketCode Module for Python.
Home-page: https://github.com/sdkwe/pywe-marketcode
Author: Hackathon
Author-email: kimi.huang@brightcells.com
License: UNKNOWN
Keywords: Wechat Weixin Market Code MarketCode
Platform: UNKNOWN
Classifier: License :: OSI Approved :: BSD License
Classifier: Programming Language :: Python
Classifier: Programming Language :: Python :: 2
Classifier: Programming Language :: Python :: 2.6
Classifier: Programming Language :: Python :: 2.7
Classifier: Programming Language :: Python :: 3
Classifier: Programming Language :: Python :: 3.2
Classifier: Programming Language :: Python :: 3.3
Classifier: Programming Language :: Python :: 3.4
Classifier: Programming Language :: Python :: 3.5
Classifier: Programming Language :: Python :: 3.6
Classifier: Programming Language :: Python :: 3.7
Classifier: Programming Language :: Python :: 3.8
Classifier: Topic :: Software Development :: Libraries :: Python Modules
Requires-Dist: furl
Requires-Dist: pywe-base (>=1.0.6)
Requires-Dist: pywe-decrypt (>=1.1.6)
Requires-Dist: pywe-token (>=1.0.6)
